{
   "1": {
        "droneType":"1",
        "actualCapacity":500,
        "warehouseId":"1",
        "batCharge":100,
        "status":"ready",
        "_id":"1"
    },
    "2": {
        "droneType":"1",
        "actualCapacity":500,
        "warehouseId":"2",
        "batCharge":100,
        "status":"ready",
        "_id":"2"
    },
    "3": {
        "droneType":"2",
        "actualCapacity":1000,
        "warehouseId":"1",
        "batCharge":100,
        "status":"ready",
        "_id":"3"
        },
    "4": {
        "droneType":"2",
        "actualCapacity":1000,
        "warehouseId":"2",
        "batCharge":100,
        "status":"ready",
        "_id":"4"
        },
    "5": {
        "droneType":"3",
        "actualCapacity":2000,
        "warehouseId":"1",
        "batCharge":100,
        "status":"ready",
        "_id":"5"
        },
    "6": {
        "droneType":"3",
        "actualCapacity":2000,
        "warehouseId":"2",
        "batCharge":100,
        "status":"ready",
        "_id":"6"
        }
}